README.rst
setup.py
generic_fk/__init__.py
generic_fk/mixins.py
generic_fk/tests.py
generic_fk/widgets.py
generic_fk.egg-info/PKG-INFO
generic_fk.egg-info/SOURCES.txt
generic_fk.egg-info/dependency_links.txt
generic_fk.egg-info/not-zip-safe
generic_fk.egg-info/requires.txt
generic_fk.egg-info/top_level.txt