Metadata-Version: 1.1
Name: generic-fk
Version: 0.1.1
Summary: Django application for GenericForeignKey
Home-page: https://github.com/DeDuHaNcHiK/django-generic-fk
Author: Tierzov Andrii
Author-email: avtierzov@gmail.com
License: UNKNOWN
Platform: UNKNOWN
Classifier: Development Status :: 5 - Production/Stable
Classifier: Environment :: Web Environment
Classifier: Intended Audience :: Developers
Classifier: License :: OSI Approved :: BSD License
Classifier: Operating System :: OS Independent
Classifier: Programming Language :: Python :: 2.7
Classifier: Programming Language :: Python :: 3.5
Classifier: Programming Language :: Python :: Implementation :: PyPy
Classifier: Framework :: Django
